expense_tracker/__init__.py
expense_tracker/api.py
expense_tracker/cli.py
expense_tracker/database.py
expense_tracker/models.py
expense_tracker/seed.py
expense_tracker/statistics.py
expense_tracker/tracker.py
expense_tracker/utils.py
expense_tracker_system-1.0.0.dist-info/METADATA
expense_tracker_system-1.0.0.dist-info/WHEEL
expense_tracker_system-1.0.0.dist-info/entry_points.txt
expense_tracker_system-1.0.0.dist-info/top_level.txt
expense_tracker_system-1.0.0.dist-info/RECORD
