Metadata-Version: 2.4
Name: expense-tracker-system
Version: 1.0.0
Summary: Expense tracker system with database persistence and API
Author-email: Ani Khachatryan <anikhachatryan565@gmail.com>
License: MIT
Project-URL: Homepage, https://github.com/Anneeie/Personal_expense_tracker
Project-URL: Bug Tracker, https://github.com/Anneeie/Personal_expense_tracker/issues
Classifier: Programming Language :: Python :: 3
Classifier: License :: OSI Approved :: MIT License
Classifier: Operating System :: OS Independent
Requires-Python: >=3.8
Requires-Dist: fastapi>=0.104.0
Requires-Dist: uvicorn>=0.24.0
Requires-Dist: sqlalchemy>=2.0.0
Requires-Dist: pydantic>=2.0.0
Requires-Dist: pandas>=2.0.0
Requires-Dist: requests>=2.31.0
Requires-Dist: aiofiles>=23.0.0
Requires-Dist: aiocsv>=1.2.0
Provides-Extra: dev
Requires-Dist: pytest>=7.0.0; extra == "dev"
Requires-Dist: pytest-asyncio>=0.21.0; extra == "dev"
Requires-Dist: httpx>=0.25.0; extra == "dev"
